google_cloud_mlflow/__init__.py
google_cloud_mlflow/_mlflow_model_gcp_deployment_utils.py
google_cloud_mlflow/_mlflow_models_docker_utils_patch.py
google_cloud_mlflow/mlflow_model_deployment_plugin_for_google_cloud_vertex_ai.py
google_cloud_mlflow/mlflow_model_registry_plugin_for_google_cloud_storage.py
google_cloud_mlflow-0.0.6.dist-info/LICENSE
google_cloud_mlflow-0.0.6.dist-info/METADATA
google_cloud_mlflow-0.0.6.dist-info/WHEEL
google_cloud_mlflow-0.0.6.dist-info/entry_points.txt
google_cloud_mlflow-0.0.6.dist-info/top_level.txt
google_cloud_mlflow-0.0.6.dist-info/RECORD
