Metadata-Version: 2.1
Name: google-cloud-mlflow
Version: 0.0.6
Summary: MLflow Google Cloud Vertex AI integration package
Home-page: https://github.com/Ark-kun/google_cloud_mlflow
Author: Alexey Volkov
Author-email: alexey.volkov@ark-kun.com
License: Apache License 2.0
Project-URL: Source, https://github.com/pypa/sampleproject/
Project-URL: Issues, https://github.com/Ark-kun/google_cloud_mlflow/issues
Keywords: mlflow,Google Cloud,Vertex AI
Classifier: License :: OSI Approved :: Apache Software License
Classifier: Natural Language :: English
Classifier: Operating System :: OS Independent
Classifier: Programming Language :: Python :: 3
Requires-Python: >=3.6
License-File: LICENSE
Requires-Dist: google-cloud-aiplatform (~=1.7)
Requires-Dist: mlflow (~=1.22)
Requires-Dist: google-cloud-build (==3.*)
Requires-Dist: google-cloud-storage (==1.*)
